LICENSE
MANIFEST.in
README.rst
pytest.ini
setup.cfg
setup.py
fawrapper/__init__.py
fawrapper/client.py
fawrapper/exceptions.py
fawrapper/requestmaker.py
fawrapper/utils.py
fawrapper.egg-info/PKG-INFO
fawrapper.egg-info/SOURCES.txt
fawrapper.egg-info/dependency_links.txt
fawrapper.egg-info/requires.txt
fawrapper.egg-info/top_level.txt
fawrapper/models/__init__.py
fawrapper/models/base.py
fawrapper/models/models.py
tests/__init__.py
tests/conftest.py
tests/test_changes.py
tests/test_item.py
tests/test_items.py
tests/test_job.py
tests/test_jobs.py
tests/test_requestmaker.py
tests/test_task.py
tests/test_tasks.py
tests/test_user.py
tests/test_users.py
tests/test_utils.py
tests/tools.py