Metadata-Version: 1.2
Name: fawrapper
Version: 0.1.0a5
Summary: A wrapper for the Fieldaware API
Home-page: https://github.com/J-Kirch/fawrapper
Author: Johnny Kirchman
Author-email: Jkirch86@gmail.com
License: MIT
Platform: UNKNOWN
Requires-Python: >3.6
